langchain_shell/__init__.py
langchain_shell/main.py
langchain_shell-0.1.1.dist-info/LICENSE
langchain_shell-0.1.1.dist-info/METADATA
langchain_shell-0.1.1.dist-info/WHEEL
langchain_shell-0.1.1.dist-info/entry_points.txt
langchain_shell-0.1.1.dist-info/RECORD
