Metadata-Version: 2.1
Name: langchain-shell
Version: 0.1.1
Summary: A shell/REPL for the LangChain programming language.
Author: Keith Hanson
Author-email: keith@keithhanson.io
Requires-Python: >=3.10,<4.0
Classifier: Programming Language :: Python :: 3
Classifier: Programming Language :: Python :: 3.10
Classifier: Programming Language :: Python :: 3.11
Requires-Dist: langchain (>=0.0.161,<0.0.162)
Requires-Dist: openai (>=0.27.6,<0.28.0)
Requires-Dist: typer (>=0.9.0,<0.10.0)
